swarm_shield/__init__.py
swarm_shield/main.py
swarm_shield-7.0.0.dist-info/LICENSE
swarm_shield-7.0.0.dist-info/METADATA
swarm_shield-7.0.0.dist-info/WHEEL
swarm_shield-7.0.0.dist-info/entry_points.txt
swarm_shield-7.0.0.dist-info/RECORD
