Metadata-Version: 2.1
Name: swarm-shield
Version: 7.0.0
Summary: Swarm Shield - TGSC
Home-page: https://github.com/The-Swarm-Corporation/swarm-shield
License: MIT
Keywords: artificial intelligence,deep learning,optimizers,Prompt Engineering,swarms,agents,llms,transformers,multi-agent,swarms of agents,Enterprise-Grade Agents,Production-Grade Agents,Agents,Multi-Grade-Agents,Swarms,Transformers,LLMs,Prompt Engineering,Agents,Generative Agents,Generative AI,Agent Marketplace,Agent Store,quant,finance,algorithmic trading,portfolio optimization,risk management,financial modeling,machine learning for finance,natural language processing for finance
Author: Kye Gomez
Author-email: kye@apac.ai
Requires-Python: >=3.10,<4.0
Classifier: Development Status :: 4 - Beta
Classifier: Intended Audience :: Developers
Classifier: License :: OSI Approved :: MIT License
Classifier: Programming Language :: Python :: 3
Classifier: Programming Language :: Python :: 3.10
Classifier: Programming Language :: Python :: 3.11
Classifier: Programming Language :: Python :: 3.12
Classifier: Topic :: Scientific/Engineering :: Artificial Intelligence
Requires-Dist: cryptography
Requires-Dist: loguru
Project-URL: Documentation, https://docs.swarms.world
Project-URL: Repository, https://github.com/The-Swarm-Corporation/swarm-shield
